wizzlethorpe/__init__.py
wizzlethorpe/cli.py
wizzlethorpe/client.py
wizzlethorpe/config.py
wizzlethorpe/models.py
wizzlethorpe/py.typed
wizzlethorpe-0.3.0.dist-info/METADATA
wizzlethorpe-0.3.0.dist-info/WHEEL
wizzlethorpe-0.3.0.dist-info/entry_points.txt
wizzlethorpe-0.3.0.dist-info/licenses/LICENSE
wizzlethorpe-0.3.0.dist-info/RECORD
