Metadata-Version: 2.4
Name: wizzlethorpe
Version: 0.3.0
Summary: Python client for Wizzlethorpe Labs APIs (Quickbrush, Cocktails)
Project-URL: Homepage, https://wizzlethorpe.com
Project-URL: Repository, https://github.com/wizzlethorpe/wizzlethorpe-python
Project-URL: Issues, https://github.com/wizzlethorpe/wizzlethorpe-python/issues
Author: Wizzlethorpe Labs
License: MIT
License-File: LICENSE
Keywords: api-client,cocktails,dnd,image-generation,quickbrush
Classifier: Development Status :: 3 - Alpha
Classifier: Intended Audience :: Developers
Classifier: License :: OSI Approved :: MIT License
Classifier: Programming Language :: Python :: 3
Classifier: Programming Language :: Python :: 3.10
Classifier: Programming Language :: Python :: 3.11
Classifier: Programming Language :: Python :: 3.12
Classifier: Topic :: Games/Entertainment :: Role-Playing
Classifier: Topic :: Software Development :: Libraries :: Python Modules
Requires-Python: >=3.10
Requires-Dist: click>=8.0
Requires-Dist: httpx>=0.27
Requires-Dist: pydantic>=2.0
Provides-Extra: dev
Requires-Dist: pytest; extra == 'dev'
Requires-Dist: ruff; extra == 'dev'
